playwithmpv/__init__.py
playwithmpv/__main__.py
playwithmpv/__version__.py
playwithmpv/server.py
playwithmpv-0.1.4.dist-info/LICENSE
playwithmpv-0.1.4.dist-info/METADATA
playwithmpv-0.1.4.dist-info/WHEEL
playwithmpv-0.1.4.dist-info/entry_points.txt
playwithmpv-0.1.4.dist-info/top_level.txt
playwithmpv-0.1.4.dist-info/RECORD
