Metadata-Version: 2.1
Name: playwithmpv
Version: 0.1.4
Summary: A server to support playing videos with mpv
Home-page: https://github.com/playallwithmpv/playwithmpv
Author: Wullic
Author-email: wenliang.ouyang@outlook.com
License: MIT
Platform: UNKNOWN
Classifier: License :: OSI Approved :: MIT License
Classifier: Programming Language :: Python
Classifier: Programming Language :: Python :: 3
Classifier: Programming Language :: Python :: 3.8
Classifier: Programming Language :: Python :: Implementation :: CPython
Classifier: Programming Language :: Python :: Implementation :: PyPy
Requires-Python: >=3.8.2
License-File: LICENSE
Requires-Dist: wheel
Requires-Dist: webargs (>=8.0.1)
Requires-Dist: Flask (>=2.0.2)
Requires-Dist: flask-cors (>=3.0.10)
Requires-Dist: youtube-dl
Requires-Dist: myst-parser
